{
  "assessmentId": "u43dhrhd",
  "transcript": "",
  "evaluation": {},
  "status": "error",
  "error": "Command failed: ffmpeg -y -i \"E:\\Lexiscore\\cefr-fluent-hub-main\\lexiscore-backend\\uploads\\1748083373452-466267449.webm\" -acodec libvorbis \"E:\\Lexiscore\\cefr-fluent-hub-main\\lexiscore-backend\\uploads\\1748083373452-466267449.webm.ogg\"\nffmpeg version 7.1.1-essentials_build-www.gyan.dev Copyright (c) 2000-2025 the FFmpeg developers\r\n  built with gcc 14.2.0 (Rev1, Built by MSYS2 project)\r\n  configuration: --enable-gpl --enable-version3 --enable-static --disable-w32threads --disable-autodetect --enable-fontconfig --enable-iconv --enable-gnutls --enable-libxml2 --enable-gmp --enable-bzlib --enable-lzma --enable-zlib --enable-libsrt --enable-libssh --enable-libzmq --enable-avisynth --enable-sdl2 --enable-libwebp --enable-libx264 --enable-libx265 --enable-libxvid --enable-libaom --enable-libopenjpeg --enable-libvpx --enable-mediafoundation --enable-libass --enable-libfreetype --enable-libfribidi --enable-libharfbuzz --enable-libvidstab --enable-libvmaf --enable-libzimg --enable-amf --enable-cuda-llvm --enable-cuvid --enable-dxva2 --enable-d3d11va --enable-d3d12va --enable-ffnvcodec --enable-libvpl --enable-nvdec --enable-nvenc --enable-vaapi --enable-libgme --enable-libopenmpt --enable-libopencore-amrwb --enable-libmp3lame --enable-libtheora --enable-libvo-amrwbenc --enable-libgsm --enable-libopencore-amrnb --enable-libopus --enable-libspeex --enable-libvorbis --enable-librubberband\r\n  libavutil      59. 39.100 / 59. 39.100\r\n  libavcodec     61. 19.101 / 61. 19.101\r\n  libavformat    61.  7.100 / 61.  7.100\r\n  libavdevice    61.  3.100 / 61.  3.100\r\n  libavfilter    10.  4.100 / 10.  4.100\r\n  libswscale      8.  3.100 /  8.  3.100\r\n  libswresample   5.  3.100 /  5.  3.100\r\n  libpostproc    58.  3.100 / 58.  3.100\r\n[matroska,webm @ 0000016c3e774a80] Format matroska,webm detected only with low score of 1, misdetection possible!\r\n[matroska,webm @ 0000016c3e774a80] EBML header parsing failed\r\n[in#0 @ 0000016c3e774680] Error opening input: Invalid data found when processing input\r\nError opening input file E:\\Lexiscore\\cefr-fluent-hub-main\\lexiscore-backend\\uploads\\1748083373452-466267449.webm.\r\nError opening input files: Invalid data found when processing input\r\n"
}